<?xml version="1.0" encoding="UTF-8"?>
<!DOCTYPE suite SYSTEM "http://testng.org/testng-1.0.dtd">
<suite name="All Test Suite" parallel="none">
    <test verbose="2" preserve-order="true" name="D:/Users/gkumarasamy/IdeaProjects/SeleniumLearning">
        <classes>
            <class name="tests2.Browser">
                <parameter name="browser" value="chrome"></parameter>
                <methods>
                    <include name="crossTest"/>
                </methods>
            </class>
            <class name="tests2.Browser">
                <parameter name="browser" value="firefox"></parameter>
                <methods>
                    <include name="crossTest"/>
                </methods>
            </class>
        </classes>
    </test>
    <test name=""
</suite>